graphdebugger/DebuggerUI.py
graphdebugger/Graph.py
graphdebugger/__init__.py
graphdebugger/run.py
graphdebugger/assets/brkp_obj.png
graphdebugger/assets/directed.png
graphdebugger/assets/dumbbell-icon-vector-10.jpg
graphdebugger/assets/fldr_obj.png
graphdebugger/assets/flow-icon-0.jpg
graphdebugger/assets/flow.png
graphdebugger/assets/new_untitled_text_file.png
graphdebugger/assets/resume_co.png
graphdebugger/assets/run_exc.png
graphdebugger/assets/save_edit.png
graphdebugger/assets/stepbystep_co.png
graphdebugger/assets/stepinto_co.png
graphdebugger/assets/stepover_co.png
graphdebugger/assets/stepreturn_co.png
graphdebugger/assets/terminate_co.png
graphdebugger/assets/weights.png
graphdebugger/graphs/dijkstra_sample.json
graphdebugger/graphs/fordfulkerson_sample.json
graphdebugger/graphs/simple_weighted.json
graphdebugger/samples/dfs.py
graphdebugger/samples/dijkstra.py
graphdebugger/samples/fordfulkerson.py
graphdebugger/samples/mst_prim.py
VisualGraphDebugger_zacharyh211-0.6.dist-info/LICENSE
VisualGraphDebugger_zacharyh211-0.6.dist-info/METADATA
VisualGraphDebugger_zacharyh211-0.6.dist-info/WHEEL
VisualGraphDebugger_zacharyh211-0.6.dist-info/entry_points.txt
VisualGraphDebugger_zacharyh211-0.6.dist-info/top_level.txt
VisualGraphDebugger_zacharyh211-0.6.dist-info/RECORD
